kv_dataplatform_consumer/__init__.py
kv_dataplatform_consumer/consume_share.py
kv_dataplatform_consumer/crypto_utils.py
kv_dataplatform_consumer-0.2.0.dist-info/LICENSE
kv_dataplatform_consumer-0.2.0.dist-info/METADATA
kv_dataplatform_consumer-0.2.0.dist-info/WHEEL
kv_dataplatform_consumer-0.2.0.dist-info/RECORD
