Metadata-Version: 2.3
Name: kv-dataplatform-consumer
Version: 0.2.0
Summary: 
Author: Jonas Mossin Wagle
Author-email: jonas.mossin@gmail.com
Requires-Python: >=3.12,<4.0
Classifier: Programming Language :: Python :: 3
Classifier: Programming Language :: Python :: 3.12
Classifier: Programming Language :: Python :: 3.13
Requires-Dist: delta-sharing (>=1.2.0,<2.0.0)
Requires-Dist: deltalake (>=0.21.0,<0.22.0)
Requires-Dist: pandas (>=2.2.3,<3.0.0)
Requires-Dist: pycryptodome (>=3.21.0,<4.0.0)
Requires-Dist: pytest (>=8.3.3,<9.0.0)
